gtshcli/__init__.py
gtshcli/exceptions.py
gtshcli/gtsh.py
gtshcli/cli/__init__.py
gtshcli/cli/branch.py
gtshcli/cli/remote.py
gtshcli/cli/repository.py
gtshcli/services/__init__.py
gtshcli/services/branch_service.py
gtshcli/services/remote_service.py
gtshcli/services/repository_service.py
gtshcli/services/subprocess_runner.py
scripts/__init__.py
scripts/branch-delete.sh
scripts/branch-list.sh
scripts/remote-merge-subtree.sh
scripts/repository-clean-up.sh
gtsh-0.1.1.dist-info/LICENSE.txt
gtsh-0.1.1.dist-info/METADATA
gtsh-0.1.1.dist-info/WHEEL
gtsh-0.1.1.dist-info/entry_points.txt
gtsh-0.1.1.dist-info/top_level.txt
gtsh-0.1.1.dist-info/RECORD
