Metadata-Version: 2.1
Name: gtsh
Version: 0.1.1
Summary: A toolbox for code janitors handle git operations withing world of git
Home-page: https://github.com/tovrleaf/git-utils
Author: Niko Kivela
Author-email: niko@tovrleaf.com
License: UNKNOWN
Keywords: git development source
Platform: UNKNOWN
Classifier: Intended Audience :: Developers
Classifier: License :: OSI Approved :: MIT License
Classifier: Programming Language :: Python :: 3
Classifier: Topic :: Software Development :: Version Control :: Git
License-File: LICENSE.txt
Requires-Dist: click (==8.0.1)
